{
  "site": {
    "title": "Macro Daily",
    "subtitle": "Daily macro briefing generated from the local macro research framework",
    "generated_at": "2026-03-28 12:43:16",
    "mode": "daily-brief"
  },
  "latest": {
    "slug": "2026-03-28",
    "date": "2026-03-28",
    "headline": "Macro input scan captured 65 candidate items across 12 working sources.",
    "summary": "Only macro-relevant items are retained. Primary sources lead the stack, while media and fast-wire items stay in the alert layer.",
    "mode": "daily-brief",
    "monitoring_strategy": "Only macro-relevant releases, policy signals, and cross-asset risk items should enter the daily brief. Official data and policy pages outrank media summaries.",
    "monitoring_layers": [
      "official-primary",
      "official-secondary",
      "media-alert"
    ],
    "monitoring_notes": [
      "Keep this project focused on macro only: policy, liquidity, rates, inflation, labor, growth, trade, FX, energy, and cross-asset risk.",
      "Exclude company news, sector-only stories, stock-specific headlines, and non-macro market color unless they clearly change the macro transmission path.",
      "Use media and fast-wire sources for alerting only, then verify important items against primary sources."
    ],
    "monitoring_sources": [
      {
        "name": "国务院 / 中国政府网要闻",
        "category": "official-primary",
        "priority": "P0",
        "region": "CN",
        "homepage_url": "https://www.gov.cn/",
        "trust_level": "primary",
        "cadence": "intraday",
        "notes": "Top-level China policy source. Use it to confirm State Council meetings, policy documents, and official briefing language."
      },
      {
        "name": "中国人民银行",
        "category": "official-primary",
        "priority": "P0",
        "region": "CN",
        "homepage_url": "http://www.pbc.gov.cn/",
        "trust_level": "primary",
        "cadence": "intraday",
        "notes": "Primary China monetary-policy and liquidity source. Relevant for OMO, LPR, FX, financial stability, and official statistical releases."
      },
      {
        "name": "国家统计局英文发布",
        "category": "official-primary",
        "priority": "P0",
        "region": "CN",
        "homepage_url": "https://www.stats.gov.cn/english/",
        "trust_level": "primary",
        "cadence": "daily",
        "notes": "Primary source for China macro data releases and statistical commentary."
      },
      {
        "name": "国家外汇管理局英文发布",
        "category": "official-secondary",
        "priority": "P1",
        "region": "CN",
        "homepage_url": "https://www.safe.gov.cn/",
        "trust_level": "primary",
        "cadence": "daily",
        "notes": "FX reserves, balance-of-payments and cross-border flow monitoring."
      },
      {
        "name": "国家发展改革委新闻动态",
        "category": "official-secondary",
        "priority": "P1",
        "region": "CN",
        "homepage_url": "https://www.ndrc.gov.cn/",
        "trust_level": "primary",
        "cadence": "daily",
        "notes": "Useful for growth policy, pricing policy, energy policy, infrastructure, and domestic-demand signals."
      },
      {
        "name": "Federal Reserve Press Releases",
        "category": "official-primary",
        "priority": "P0",
        "region": "US",
        "homepage_url": "https://www.federalreserve.gov/feeds/feeds.htm",
        "trust_level": "primary",
        "cadence": "intraday",
        "notes": "Primary source for Fed policy, facilities, supervision, and liquidity announcements."
      },
      {
        "name": "Federal Reserve Speeches",
        "category": "official-secondary",
        "priority": "P1",
        "region": "US",
        "homepage_url": "https://www.federalreserve.gov/newsevents/speeches.htm",
        "trust_level": "primary",
        "cadence": "daily",
        "notes": "Good for Fed communication drift and policy tone before formal meeting outcomes change."
      },
      {
        "name": "U.S. Bureau of Labor Statistics Newsroom",
        "category": "official-primary",
        "priority": "P0",
        "region": "US",
        "homepage_url": "https://www.bls.gov/",
        "trust_level": "primary",
        "cadence": "daily",
        "notes": "Primary U.S. labor and inflation release source."
      },
      {
        "name": "U.S. Bureau of Economic Analysis Current Releases",
        "category": "official-primary",
        "priority": "P0",
        "region": "US",
        "homepage_url": "https://www.bea.gov/news/current-releases",
        "trust_level": "primary",
        "cadence": "daily",
        "notes": "Primary U.S. GDP, PCE, income, trade, and sector-activity release source."
      },
      {
        "name": "IMF News and Press Releases",
        "category": "official-secondary",
        "priority": "P1",
        "region": "Global",
        "homepage_url": "https://www.imf.org/en/News",
        "trust_level": "primary",
        "cadence": "daily",
        "notes": "Helpful for global macro backdrop, spillovers, and multilateral policy framing."
      },
      {
        "name": "财联社电报",
        "category": "media-alert",
        "priority": "P1",
        "region": "CN",
        "homepage_url": "https://www.cls.cn/telegraph",
        "trust_level": "secondary",
        "cadence": "intraday",
        "notes": "Highest-frequency China-friendly macro alert stream. Every important item still needs primary-source confirmation."
      },
      {
        "name": "财联社深度",
        "category": "media-alert",
        "priority": "P1",
        "region": "CN",
        "homepage_url": "https://www.cls.cn/",
        "trust_level": "secondary",
        "cadence": "intraday",
        "notes": "Macro-oriented depth and interpretation layer from 财联社 homepage. Use it as a context supplement, not as the final authority."
      },
      {
        "name": "Reuters Markets",
        "category": "media-alert",
        "priority": "P2",
        "region": "Global",
        "homepage_url": "https://www.reuters.com/markets/",
        "trust_level": "secondary",
        "cadence": "intraday",
        "notes": "Disabled for now because direct site fetching is not stable in the current environment."
      }
    ],
    "daily_input_counts": {
      "sources_ok": 12,
      "sources_failed": 0,
      "items_total": 65
    },
    "daily_input_generated_at": "2026-03-28 12:43:16",
    "watchpoints": [
      "China policy radar: 李强主持召开国务院常务会议 学习贯彻习近平总书记在深入推进雄安新区高质量建设和发展座谈会上的重要讲话精神",
      "China data monitor: SAFE Releases Data on Foreign Exchange Settlement and Sales ...",
      "Fed and U.S. macro: U.S. International Transactions and Investment Position, 4th Quarter and Year 2025",
      "Global macro and cross-asset risk: World Economic Outlook"
    ],
    "source_documents": [
      "F:\\cursor\\research-report\\learning\\02-macro-synthesis\\macro-research-motherboard.md",
      "F:\\cursor\\research-report\\learning\\02-macro-synthesis\\macro-transmission-map.md",
      "F:\\cursor\\research-report\\learning\\02-macro-synthesis\\macro-misjudgment-and-falsification.md",
      "F:\\cursor\\research-report\\learning\\02-macro-synthesis\\macro-to-industry-interfaces.md",
      "F:\\cursor\\research-report\\playbooks\\macro-strategy-general-playbook.md",
      "F:\\cursor\\research-report\\capability\\macro-strategy-general.md",
      "F:\\cursor\\research-report\\source-registry.json",
      "F:\\cursor\\research-report\\_work\\macro-daily\\daily-brief-latest.json"
    ],
    "sections": [
      {
        "title": "China policy radar",
        "hint": "Read this first when the market is trading China policy tone, liquidity, fiscal support, or administrative guidance.",
        "items": [
          {
            "kind": "entry",
            "title": "李强主持召开国务院常务会议 学习贯彻习近平总书记在深入推进雄安新区高质量建设和发展座谈会上的重要讲话精神",
            "url": "https://www.gov.cn/yaowen/liebiao/202603/content_7064015.htm",
            "meta": "国务院 / 中国政府网要闻 | P0 | primary",
            "summary": "李强主持召开国务院常务会议 学习贯彻习近平总书记在深入推进雄安新区高质量建设和发展座谈会上的重要讲话精神"
          },
          {
            "kind": "entry",
            "title": "国家对成品油价格采取临时调控措施",
            "url": "https://www.ndrc.gov.cn/xwdt/xwfb/202603/t20260323_1404296.html",
            "meta": "国家发展改革委新闻动态 | P1 | primary | 2026/03/23",
            "summary": "新闻发布 | Useful for growth policy, pricing policy, energy policy, infrastructure, and domestic-demand signals."
          },
          {
            "kind": "entry",
            "title": "中国人民银行货币政策委员会...",
            "url": "http://www.pbc.gov.cn/zhengcehuobisi/125207/3870933/3870939/5546206/index.html",
            "meta": "中国人民银行 | P0 | primary",
            "summary": "Primary China monetary-policy and liquidity source. Relevant for OMO, LPR, FX, financial stability, and official statistical releases."
          },
          {
            "kind": "entry",
            "title": "中国人民银行货币政策委员会...",
            "url": "http://www.pbc.gov.cn/zhengcehuobisi/125207/3870933/3870936/2025100917194615589/index.html",
            "meta": "中国人民银行 | P0 | primary",
            "summary": "Primary China monetary-policy and liquidity source. Relevant for OMO, LPR, FX, financial stability, and official statistical releases."
          },
          {
            "kind": "entry",
            "title": "中国人民银行召开2026年金融稳定工作会议",
            "url": "http://www.pbc.gov.cn/goutongjiaoliu/113456/113469/2026032711215379505/index.html",
            "meta": "中国人民银行 | P0 | primary",
            "summary": "Primary China monetary-policy and liquidity source. Relevant for OMO, LPR, FX, financial stability, and official statistical releases."
          },
          {
            "kind": "entry",
            "title": "2026年3月23日国内成品油价格调整",
            "url": "https://www.ndrc.gov.cn/xwdt/xwfb/202603/t20260323_1404295.html",
            "meta": "国家发展改革委新闻动态 | P1 | primary | 2026/03/23",
            "summary": "新闻发布 | Useful for growth policy, pricing policy, energy policy, infrastructure, and domestic-demand signals."
          }
        ]
      },
      {
        "title": "China data monitor",
        "hint": "Use this to check whether the China macro tape is confirming or contradicting the current policy narrative.",
        "items": [
          {
            "kind": "entry",
            "title": "SAFE Releases Data on Foreign Exchange Settlement and Sales ...",
            "url": "https://www.safe.gov.cn/en/2026/0316/2400.html",
            "meta": "国家外汇管理局英文发布 | P1 | primary",
            "summary": "FX reserves, balance-of-payments and cross-border flow monitoring."
          },
          {
            "kind": "entry",
            "title": "SAFE Releases Data on China's Foreign Exchange Reserves at t...",
            "url": "https://www.safe.gov.cn/en/2026/0307/2403.html",
            "meta": "国家外汇管理局英文发布 | P1 | primary",
            "summary": "FX reserves, balance-of-payments and cross-border flow monitoring."
          },
          {
            "kind": "entry",
            "title": "SAFE Releases China's Balance of Payments for the Fourth Qua...",
            "url": "https://www.safe.gov.cn/en/2026/0327/2406.html",
            "meta": "国家外汇管理局英文发布 | P1 | primary",
            "summary": "FX reserves, balance-of-payments and cross-border flow monitoring."
          },
          {
            "kind": "entry",
            "title": "Notice of the State Administration of Foreign Exchange on Fu...",
            "url": "https://www.safe.gov.cn/en/2023/1208/2262.html",
            "meta": "国家外汇管理局英文发布 | P1 | primary",
            "summary": "FX reserves, balance-of-payments and cross-border flow monitoring."
          },
          {
            "kind": "entry",
            "title": "Circular of the State Administration of Foreign Exchange on ...",
            "url": "https://www.safe.gov.cn/en/2021/1203/1909.html",
            "meta": "国家外汇管理局英文发布 | P1 | primary",
            "summary": "FX reserves, balance-of-payments and cross-border flow monitoring."
          },
          {
            "kind": "entry",
            "title": "Circular of the State Administration of Foreign Exchange on ...",
            "url": "https://www.safe.gov.cn/en/2021/0108/1792.html",
            "meta": "国家外汇管理局英文发布 | P1 | primary",
            "summary": "FX reserves, balance-of-payments and cross-border flow monitoring."
          }
        ]
      },
      {
        "title": "Fed and U.S. macro",
        "hint": "This bucket matters when global duration, dollar direction, and risk appetite are leading markets.",
        "items": [
          {
            "kind": "entry",
            "title": "U.S. International Transactions and Investment Position, 4th Quarter and Year 2025",
            "url": "https://www.bea.gov/news/2026/us-international-transactions-and-investment-position-4th-quarter-and-year-2025",
            "meta": "U.S. Bureau of Economic Analysis Current Releases | P0 | primary",
            "summary": "Primary U.S. GDP, PCE, income, trade, and sector-activity release source."
          },
          {
            "kind": "entry",
            "title": "U.S. International Trade in Goods and Services, January 2026",
            "url": "https://www.bea.gov/news/2026/us-international-trade-goods-and-services-january-2026",
            "meta": "U.S. Bureau of Economic Analysis Current Releases | P0 | primary",
            "summary": "Primary U.S. GDP, PCE, income, trade, and sector-activity release source."
          },
          {
            "kind": "entry",
            "title": "Real Personal Consumption Expenditures by State and Real Personal Income by State, 2024",
            "url": "https://www.bea.gov/news/2026/real-personal-consumption-expenditures-state-and-real-personal-income-state-2024",
            "meta": "U.S. Bureau of Economic Analysis Current Releases | P0 | primary",
            "summary": "Primary U.S. GDP, PCE, income, trade, and sector-activity release source."
          },
          {
            "kind": "entry",
            "title": "Personal Income and Outlays, January 2026",
            "url": "https://www.bea.gov/news/2026/personal-income-and-outlays-january-2026",
            "meta": "U.S. Bureau of Economic Analysis Current Releases | P0 | primary",
            "summary": "Primary U.S. GDP, PCE, income, trade, and sector-activity release source."
          },
          {
            "kind": "entry",
            "title": "Gross Domestic Product by State and Personal Income by State, 3rd Quarter 2025",
            "url": "https://www.bea.gov/news/2026/gross-domestic-product-state-and-personal-income-state-3rd-quarter-2025",
            "meta": "U.S. Bureau of Economic Analysis Current Releases | P0 | primary",
            "summary": "Primary U.S. GDP, PCE, income, trade, and sector-activity release source."
          },
          {
            "kind": "entry",
            "title": "Gross Domestic Product by County and Personal Income by County, 2024",
            "url": "https://www.bea.gov/news/2026/gross-domestic-product-county-and-personal-income-county-2024",
            "meta": "U.S. Bureau of Economic Analysis Current Releases | P0 | primary",
            "summary": "Primary U.S. GDP, PCE, income, trade, and sector-activity release source."
          }
        ]
      },
      {
        "title": "Global macro and cross-asset risk",
        "hint": "Use this to track spillovers from oil, geopolitics, trade, IMF framing, and broader cross-asset stress.",
        "items": [
          {
            "kind": "entry",
            "title": "World Economic Outlook",
            "url": "https://www.imf.org/en/publications/weo",
            "meta": "IMF News and Press Releases | P1 | primary",
            "summary": "Helpful for global macro backdrop, spillovers, and multilateral policy framing."
          },
          {
            "kind": "entry",
            "title": "How the IMF Supports the Global Economy",
            "url": "https://www.imf.org/en/about/how-the-imf-supports-the-global-economy",
            "meta": "IMF News and Press Releases | P1 | primary",
            "summary": "Helpful for global macro backdrop, spillovers, and multilateral policy framing."
          },
          {
            "kind": "entry",
            "title": "Global Financial Stability Report",
            "url": "https://www.imf.org/en/publications/gfsr",
            "meta": "IMF News and Press Releases | P1 | primary",
            "summary": "Helpful for global macro backdrop, spillovers, and multilateral policy framing."
          },
          {
            "kind": "entry",
            "title": "Fiscal Policies",
            "url": "https://www.imf.org/en/topics/fiscal-policies",
            "meta": "IMF News and Press Releases | P1 | primary",
            "summary": "Helpful for global macro backdrop, spillovers, and multilateral policy framing."
          },
          {
            "kind": "entry",
            "title": "Fiscal Monitor",
            "url": "https://www.imf.org/en/publications/fm",
            "meta": "IMF News and Press Releases | P1 | primary",
            "summary": "Helpful for global macro backdrop, spillovers, and multilateral policy framing."
          },
          {
            "kind": "entry",
            "title": "Economic Outlook",
            "url": "https://www.imf.org/en/videos/index#economicoutlook",
            "meta": "IMF News and Press Releases | P1 | primary",
            "summary": "Helpful for global macro backdrop, spillovers, and multilateral policy framing."
          }
        ]
      },
      {
        "title": "Media alerts worth verifying",
        "hint": "These are fast macro signals and framing aids. Confirm anything important against primary sources before treating it as final.",
        "items": [
          {
            "kind": "entry",
            "title": "美国消费者信心跌至三个月低点 最富裕阶层也因股市重挫遭受打击",
            "url": "https://www.cls.cn/detail/2327642",
            "meta": "财联社深度 | P1 | secondary | 2026-03-28 00:55:35",
            "summary": "①3月份美国消费者信心降至53.3，为去年12月以来最低水平，主要受中东战争引发的通胀忧虑和经济前景不确定性影响； ②若美伊战争持续数月，经济前景可能迅速恶化，引发下行螺旋：股市下跌导致支出减弱，最终陷入衰退。"
          },
          {
            "kind": "entry",
            "title": "航空燃油价格短短一个月翻倍 一场全球“飞行危机”正在显现",
            "url": "https://www.cls.cn/detail/2327671",
            "meta": "财联社深度 | P1 | secondary | 2026-03-28 03:25:58",
            "summary": "①中东战事持续冲击全球能源供应链，航空煤油价格自开战以来已从约800美元/吨飙升至1600美元/吨，亚洲多国航空公司开始停飞或削减航班； ②分析指出，欧洲最快5月或出现燃油短缺； ③对于乘客来说，过去一个月也经历了燃油附加费的飞涨。"
          },
          {
            "kind": "entry",
            "title": "美国总统特使预计本周将与伊朗举行会谈；央行召开2026年金融稳定工作会议",
            "url": "https://www.cls.cn/detail/2327698",
            "meta": "财联社深度 | P1 | secondary | 2026-03-28 07:00:00",
            "summary": "①中方对美方启动两项贸易壁垒调查②央行召开2026年金融稳定工作会议③两部门：根据空间业务实际占用带宽向卫星运营商收取无线电频率占用费④美国总统特使预计本周将与伊朗举行会谈⑤工商银行、建设银行等披露2025年年报。"
          },
          {
            "kind": "entry",
            "title": "欧盟官员警告欧盟经济正面临滞胀风险",
            "url": "https://www.cls.cn/detail/2327780",
            "meta": "财联社电报 | P1 | secondary | 2026-03-28 11:07:11",
            "summary": "【欧盟官员警告欧盟经济正面临滞胀风险】财联社3月28日电，欧盟委员会负责经济事务的委员瓦尔季斯·东布罗夫斯基斯27日表示，由于中东战事引发能源价格飙升，欧盟经济正面临滞胀风险。当天，欧元集团就能源价格问题举行线上会议。东布罗夫斯基斯在会后召开的新闻发布会上表示，“前景被高度的不确定性笼罩”，欧盟经济正面临滞胀风险，即经济增长放缓与通胀上升并存的局面。“即便能源供应受阻时间相对短暂，也会出现这种情况。”分析表明，2026年欧盟经济增..."
          },
          {
            "kind": "entry",
            "title": "“末日博士”鲁比尼：特朗普更有可能升级伊朗局势而非选择退让",
            "url": "https://www.cls.cn/detail/2327594",
            "meta": "财联社深度 | P1 | secondary | 2026-03-27 23:25:36",
            "summary": "①著名经济学家鲁比尼预测，美国总统特朗普可能选择升级对伊朗的冲突以争取胜利，而非退让。他认为冲突升级的概率超过50%； ②鲁比尼警告称，冲突持续将对全球经济造成冲击，可能导致油价上涨、各国下调经济增长预期，并可能迫使美联储和欧洲央行加息。"
          },
          {
            "kind": "entry",
            "title": "巴防务分析专家：巴基斯坦正在美伊间发挥协调与斡旋作用",
            "url": "https://www.cls.cn/detail/2327785",
            "meta": "财联社电报 | P1 | secondary | 2026-03-28 11:18:35",
            "summary": "【巴防务分析专家：巴基斯坦正在美伊间发挥协调与斡旋作用】财联社3月28日电，巴基斯坦外交部长达尔26日证实，美伊间接谈判正通过由巴基斯坦传递信息的方式进行。对此，巴基斯坦防务分析专家贾维德·伊克巴尔在接受总台记者采访时表示，当前局势复杂，巴基斯坦正在美伊两国间发挥协调与斡旋作用。防务分析专家贾维德·伊克巴尔：这一角色源于我们关键的地理位置和我们的外交政策，以及我们与该地区和这场冲突中，除以色列以外的所有重要利益攸关方的良好关系。在..."
          }
        ]
      },
      {
        "title": "Official primary releases",
        "items": [
          {
            "kind": "entry",
            "title": "李强主持召开国务院常务会议 学习贯彻习近平总书记在深入推进雄安新区高质量建设和发展座谈会上的重要讲话精神",
            "url": "https://www.gov.cn/yaowen/liebiao/202603/content_7064015.htm",
            "meta": "国务院 / 中国政府网要闻 | P0 | primary",
            "summary": "李强主持召开国务院常务会议 学习贯彻习近平总书记在深入推进雄安新区高质量建设和发展座谈会上的重要讲话精神"
          },
          {
            "kind": "entry",
            "title": "中共中央政治局召开会议 审议《中国共产党地方委员会工作条例》 中共中央总书记习近平主持会议",
            "url": "https://www.gov.cn/yaowen/liebiao/202603/content_7063982.htm",
            "meta": "国务院 / 中国政府网要闻 | P0 | primary",
            "summary": "中共中央政治局召开会议 审议《中国共产党地方委员会工作条例》 中共中央总书记习近平主持会议"
          },
          {
            "kind": "entry",
            "title": "十四届全国人大四次会议8406件代表建议统一交办",
            "url": "https://www.gov.cn/yaowen/liebiao/202603/content_7063893.htm",
            "meta": "国务院 / 中国政府网要闻 | P0 | primary",
            "summary": "十四届全国人大四次会议8406件代表建议统一交办"
          },
          {
            "kind": "entry",
            "title": "李强签署国务院令 公布修订后的《全国农业普查条例》",
            "url": "https://www.gov.cn/yaowen/liebiao/202603/content_7063867.htm",
            "meta": "国务院 / 中国政府网要闻 | P0 | primary",
            "summary": "李强签署国务院令 公布修订后的《全国农业普查条例》"
          },
          {
            "kind": "entry",
            "title": "王毅向《海洋生物多样性协定》第三届筹委会会议致辞",
            "url": "https://www.gov.cn/yaowen/liebiao/202603/content_7063804.htm",
            "meta": "国务院 / 中国政府网要闻 | P0 | primary",
            "summary": "王毅向《海洋生物多样性协定》第三届筹委会会议致辞"
          },
          {
            "kind": "entry",
            "title": "中共中央办公厅 国务院办公厅关于加快建立长期护理保险制度的意见",
            "url": "https://www.gov.cn/yaowen/liebiao/202603/content_7063789.htm",
            "meta": "国务院 / 中国政府网要闻 | P0 | primary",
            "summary": "中共中央办公厅 国务院办公厅关于加快建立长期护理保险制度的意见"
          },
          {
            "kind": "entry",
            "title": "国务院任免国家工作人员（2026年3月25日）",
            "url": "https://www.gov.cn/yaowen/liebiao/202603/content_7063727.htm",
            "meta": "国务院 / 中国政府网要闻 | P0 | primary",
            "summary": "国务院任免国家工作人员（2026年3月25日）"
          },
          {
            "kind": "entry",
            "title": "各地打造消费新场景 激发市场新活力",
            "url": "https://www.gov.cn/yaowen/liebiao/202603/content_7063656.htm",
            "meta": "国务院 / 中国政府网要闻 | P0 | primary",
            "summary": "各地打造消费新场景 激发市场新活力"
          },
          {
            "kind": "entry",
            "title": "中国人民银行召开2026年金融稳定工作会议",
            "url": "http://www.pbc.gov.cn/goutongjiaoliu/113456/113469/2026032711215379505/index.html",
            "meta": "中国人民银行 | P0 | primary",
            "summary": "Primary China monetary-policy and liquidity source. Relevant for OMO, LPR, FX, financial stability, and official statistical releases."
          },
          {
            "kind": "entry",
            "title": "中国人民银行召开2026年国库工作会议",
            "url": "http://www.pbc.gov.cn/goutongjiaoliu/113456/113469/2026032315013158591/index.html",
            "meta": "中国人民银行 | P0 | primary",
            "summary": "Primary China monetary-policy and liquidity source. Relevant for OMO, LPR, FX, financial stability, and official statistical releases."
          },
          {
            "kind": "entry",
            "title": "中国人民银行货币政策委员会...",
            "url": "http://www.pbc.gov.cn/zhengcehuobisi/125207/3870933/3870939/5546206/index.html",
            "meta": "中国人民银行 | P0 | primary",
            "summary": "Primary China monetary-policy and liquidity source. Relevant for OMO, LPR, FX, financial stability, and official statistical releases."
          },
          {
            "kind": "entry",
            "title": "中国人民银行货币政策委员会...",
            "url": "http://www.pbc.gov.cn/zhengcehuobisi/125207/3870933/3870936/2025100917194615589/index.html",
            "meta": "中国人民银行 | P0 | primary",
            "summary": "Primary China monetary-policy and liquidity source. Relevant for OMO, LPR, FX, financial stability, and official statistical releases."
          }
        ]
      },
      {
        "title": "Official secondary context",
        "items": [
          {
            "kind": "entry",
            "title": "SAFE Releases China's Balance of Payments for the Fourth Qua...",
            "url": "https://www.safe.gov.cn/en/2026/0327/2406.html",
            "meta": "国家外汇管理局英文发布 | P1 | primary",
            "summary": "FX reserves, balance-of-payments and cross-border flow monitoring."
          },
          {
            "kind": "entry",
            "title": "SAFE Releases Data on Foreign Exchange Settlement and Sales ...",
            "url": "https://www.safe.gov.cn/en/2026/0316/2400.html",
            "meta": "国家外汇管理局英文发布 | P1 | primary",
            "summary": "FX reserves, balance-of-payments and cross-border flow monitoring."
          },
          {
            "kind": "entry",
            "title": "SAFE Releases Data on China's Foreign Exchange Reserves at t...",
            "url": "https://www.safe.gov.cn/en/2026/0307/2403.html",
            "meta": "国家外汇管理局英文发布 | P1 | primary",
            "summary": "FX reserves, balance-of-payments and cross-border flow monitoring."
          },
          {
            "kind": "entry",
            "title": "Notice of the State Administration of Foreign Exchange on Fu...",
            "url": "https://www.safe.gov.cn/en/2023/1208/2262.html",
            "meta": "国家外汇管理局英文发布 | P1 | primary",
            "summary": "FX reserves, balance-of-payments and cross-border flow monitoring."
          },
          {
            "kind": "entry",
            "title": "Circular of the State Administration of Foreign Exchange on ...",
            "url": "https://www.safe.gov.cn/en/2021/1203/1909.html",
            "meta": "国家外汇管理局英文发布 | P1 | primary",
            "summary": "FX reserves, balance-of-payments and cross-border flow monitoring."
          },
          {
            "kind": "entry",
            "title": "Circular of the State Administration of Foreign Exchange on ...",
            "url": "https://www.safe.gov.cn/en/2021/0108/1792.html",
            "meta": "国家外汇管理局英文发布 | P1 | primary",
            "summary": "FX reserves, balance-of-payments and cross-border flow monitoring."
          },
          {
            "kind": "entry",
            "title": "国家对成品油价格采取临时调控措施",
            "url": "https://www.ndrc.gov.cn/xwdt/xwfb/202603/t20260323_1404296.html",
            "meta": "国家发展改革委新闻动态 | P1 | primary | 2026/03/23",
            "summary": "新闻发布 | Useful for growth policy, pricing policy, energy policy, infrastructure, and domestic-demand signals."
          },
          {
            "kind": "entry",
            "title": "2026年3月23日国内成品油价格调整",
            "url": "https://www.ndrc.gov.cn/xwdt/xwfb/202603/t20260323_1404295.html",
            "meta": "国家发展改革委新闻动态 | P1 | primary | 2026/03/23",
            "summary": "新闻发布 | Useful for growth policy, pricing policy, energy policy, infrastructure, and domestic-demand signals."
          },
          {
            "kind": "entry",
            "title": "关于加强投资项目在线审批监管平台和工程建设项目审批管理系统数据共享的通知",
            "url": "https://www.ndrc.gov.cn/xwdt/tzgg/202602/t20260213_1403764.html",
            "meta": "国家发展改革委新闻动态 | P1 | primary | 2026/02/13",
            "summary": "通知公告 | Useful for growth policy, pricing policy, energy policy, infrastructure, and domestic-demand signals."
          },
          {
            "kind": "entry",
            "title": "Bowman, Capital Rules for the Real Economy",
            "url": "https://www.federalreserve.gov/newsevents/speech/bowman20260312a.htm",
            "meta": "Federal Reserve Speeches | P1 | primary | Thu, 12 Mar 2026 15:00:00 GMT",
            "summary": "Speech At the Cato Institute Policy Forum: Basel III and Bank Capital Rules, Washington, D.C."
          },
          {
            "kind": "entry",
            "title": "Cook, Opening Remarks for the “AI and Productivity across the Economy” Panel",
            "url": "https://www.federalreserve.gov/newsevents/speech/cook20260224a.htm",
            "meta": "Federal Reserve Speeches | P1 | primary | Tue, 24 Feb 2026 14:30:00 GMT",
            "summary": "Speech At “The Great Realignment: Navigating AI, Demographic, and Geoeconomic Shifts,” 42nd Annual NABE Economic Policy Conference, Washington, D.C."
          },
          {
            "kind": "entry",
            "title": "Waller, Labor Market Data: Signal or Noise?",
            "url": "https://www.federalreserve.gov/newsevents/speech/waller20260223a.htm",
            "meta": "Federal Reserve Speeches | P1 | primary | Mon, 23 Feb 2026 13:00:00 GMT",
            "summary": "Speech At The Great Realignment: Navigating AI, Demographic and Geoeconomic Change, 42nd Annual NABE Economic Policy Conference, The National Association for Business Economics, Washington, D.C."
          }
        ]
      },
      {
        "title": "Media and fast-wire alerts",
        "items": [
          {
            "kind": "entry",
            "title": "巴防务分析专家：巴基斯坦正在美伊间发挥协调与斡旋作用",
            "url": "https://www.cls.cn/detail/2327785",
            "meta": "财联社电报 | P1 | secondary | 2026-03-28 11:18:35",
            "summary": "【巴防务分析专家：巴基斯坦正在美伊间发挥协调与斡旋作用】财联社3月28日电，巴基斯坦外交部长达尔26日证实，美伊间接谈判正通过由巴基斯坦传递信息的方式进行。对此，巴基斯坦防务分析专家贾维德·伊克巴尔在接受总台记者采访时表示，当前局势复杂，巴基斯坦正在美伊两国间发挥协调与斡旋作用。防务分析专家贾维德·伊克巴尔：这一角色源于我们关键的地理位置和我们的外交政策，以及我们与该地区和这场冲突中，除以色列以外的所有重要利益攸关方的良好关系。在..."
          },
          {
            "kind": "entry",
            "title": "欧盟官员警告欧盟经济正面临滞胀风险",
            "url": "https://www.cls.cn/detail/2327780",
            "meta": "财联社电报 | P1 | secondary | 2026-03-28 11:07:11",
            "summary": "【欧盟官员警告欧盟经济正面临滞胀风险】财联社3月28日电，欧盟委员会负责经济事务的委员瓦尔季斯·东布罗夫斯基斯27日表示，由于中东战事引发能源价格飙升，欧盟经济正面临滞胀风险。当天，欧元集团就能源价格问题举行线上会议。东布罗夫斯基斯在会后召开的新闻发布会上表示，“前景被高度的不确定性笼罩”，欧盟经济正面临滞胀风险，即经济增长放缓与通胀上升并存的局面。“即便能源供应受阻时间相对短暂，也会出现这种情况。”分析表明，2026年欧盟经济增..."
          },
          {
            "kind": "entry",
            "title": "美国消费者信心跌至三个月低点 最富裕阶层也因股市重挫遭受打击",
            "url": "https://www.cls.cn/detail/2327642",
            "meta": "财联社深度 | P1 | secondary | 2026-03-28 00:55:35",
            "summary": "①3月份美国消费者信心降至53.3，为去年12月以来最低水平，主要受中东战争引发的通胀忧虑和经济前景不确定性影响； ②若美伊战争持续数月，经济前景可能迅速恶化，引发下行螺旋：股市下跌导致支出减弱，最终陷入衰退。"
          },
          {
            "kind": "entry",
            "title": "美国总统特使预计本周将与伊朗举行会谈；央行召开2026年金融稳定工作会议",
            "url": "https://www.cls.cn/detail/2327698",
            "meta": "财联社深度 | P1 | secondary | 2026-03-28 07:00:00",
            "summary": "①中方对美方启动两项贸易壁垒调查②央行召开2026年金融稳定工作会议③两部门：根据空间业务实际占用带宽向卫星运营商收取无线电频率占用费④美国总统特使预计本周将与伊朗举行会谈⑤工商银行、建设银行等披露2025年年报。"
          },
          {
            "kind": "entry",
            "title": "航空燃油价格短短一个月翻倍 一场全球“飞行危机”正在显现",
            "url": "https://www.cls.cn/detail/2327671",
            "meta": "财联社深度 | P1 | secondary | 2026-03-28 03:25:58",
            "summary": "①中东战事持续冲击全球能源供应链，航空煤油价格自开战以来已从约800美元/吨飙升至1600美元/吨，亚洲多国航空公司开始停飞或削减航班； ②分析指出，欧洲最快5月或出现燃油短缺； ③对于乘客来说，过去一个月也经历了燃油附加费的飞涨。"
          },
          {
            "kind": "entry",
            "title": "“末日博士”鲁比尼：特朗普更有可能升级伊朗局势而非选择退让",
            "url": "https://www.cls.cn/detail/2327594",
            "meta": "财联社深度 | P1 | secondary | 2026-03-27 23:25:36",
            "summary": "①著名经济学家鲁比尼预测，美国总统特朗普可能选择升级对伊朗的冲突以争取胜利，而非退让。他认为冲突升级的概率超过50%； ②鲁比尼警告称，冲突持续将对全球经济造成冲击，可能导致油价上涨、各国下调经济增长预期，并可能迫使美联储和欧洲央行加息。"
          }
        ]
      },
      {
        "title": "Framework line",
        "items": [
          "Start from the core contradiction instead of starting from the latest price move.",
          "Treat macro research as a transmission grammar that can later plug into industry work.",
          "Separate leading variables from confirmation variables before assigning market weight."
        ]
      },
      {
        "title": "Transmission map",
        "items": [
          "Base path: policy -> rates -> credit -> FX/liquidity -> risk appetite -> asset pricing.",
          "Fast paths can begin from flows, positioning, or geopolitics, but they still need to reconnect to the same macro chain.",
          "Do not confuse the end-point asset move with the true starting variable."
        ]
      },
      {
        "title": "First 30-minute checklist",
        "items": [
          "Confirm listing status and market context.",
          "Identify the industry archetype.",
          "Pull the last 2-3 strongest reports, not the full archive.",
          "Write the core contradiction in one sentence.",
          "List the top 5 tracking indicators.",
          "List the top 3 disconfirmation risks."
        ]
      },
      {
        "title": "Core research questions",
        "items": [
          "Question 1: What is the current core contradiction in this industry framework set?",
          "Question 2: Which variables explain revenue and margin changes first?",
          "Question 3: Which leading indicators move before earnings revisions?",
          "Question 4: Which sub-segments or company types map to different KPI sets?",
          "Question 5: Which policy or macro variables can invalidate the base case?",
          "Question 6: Which valuation anchors are actually used in the report set?"
        ]
      },
      {
        "title": "Risk and falsification",
        "items": [
          "Do not reverse-engineer a macro story from a price move that has already happened.",
          "A single data point is not a macro cycle turn unless it persists and enters the transmission chain.",
          "Write the failure condition explicitly: which leading variable would invalidate the current line first?",
          "Distinguish timing lag from thesis failure before downgrading a framework."
        ]
      },
      {
        "title": "Macro-to-industry interfaces",
        "items": [
          "Technology usually receives macro through liquidity, valuation, and risk appetite rather than through the first data print.",
          "Financials receive macro directly through rates, credit, regulation, and balance-sheet quality.",
          "Resources and materials receive macro through global demand, the dollar, inventory, and price transmission.",
          "Consumer and autos often receive macro through income expectations, confidence, policy stimulus, and financing access."
        ]
      }
    ]
  },
  "history": [
    {
      "slug": "2026-03-28",
      "date": "2026-03-28",
      "headline": "Daily macro brief",
      "status": "daily-brief"
    }
  ]
}
